vc2_data_tables/__init__.py
vc2_data_tables/csv_readers.py
vc2_data_tables/version.py
vc2_data_tables/csv/base_video_format_parameters.csv
vc2_data_tables/csv/levels.csv
vc2_data_tables/csv/preset_color_matrices.csv
vc2_data_tables/csv/preset_color_primaries.csv
vc2_data_tables/csv/preset_color_specs.csv
vc2_data_tables/csv/preset_frame_rates.csv
vc2_data_tables/csv/preset_pixel_aspect_ratios.csv
vc2_data_tables/csv/preset_signal_ranges.csv
vc2_data_tables/csv/preset_transfer_functions.csv
vc2_data_tables/csv/profiles.csv
vc2_data_tables/csv/quantisation_matrices.csv
vc2_data_tables-2.0.0.dist-info/LICENSE.txt
vc2_data_tables-2.0.0.dist-info/METADATA
vc2_data_tables-2.0.0.dist-info/WHEEL
vc2_data_tables-2.0.0.dist-info/entry_points.txt
vc2_data_tables-2.0.0.dist-info/top_level.txt
vc2_data_tables-2.0.0.dist-info/RECORD
