Metadata-Version: 2.1
Name: vc2-data-tables
Version: 2.0.0
Summary: Machine-readable constants and data tables for the SMPTE ST 2042-1 VC-2 professional video codec.
Home-page: https://github.com/bbc/vc2_data_tables
Author: BBC R&D
License: GPL-3.0-only
Keywords: vc2 dirac dirac-pro constants data-tables quantisation-matrix
Platform: UNKNOWN
Classifier: Development Status :: 5 - Production/Stable
Classifier: Intended Audience :: Developers
Classifier: Intended Audience :: Manufacturing
Classifier: Intended Audience :: Information Technology
Classifier: Intended Audience :: Telecommunications Industry
Classifier: License :: OSI Approved :: GNU General Public License v3 (GPLv3)
Classifier: Operating System :: POSIX :: Linux
Classifier: Operating System :: Microsoft :: Windows
Classifier: Operating System :: MacOS
Classifier: Programming Language :: Python :: 2
Classifier: Programming Language :: Python :: 2.7
Classifier: Programming Language :: Python :: 3
Classifier: Programming Language :: Python :: 3.6
Classifier: Programming Language :: Python :: 3.7
Classifier: Programming Language :: Python :: 3.8
Classifier: Programming Language :: Python :: 3.9
License-File: LICENSE.txt
Requires-Dist: enum34 ; python_version < "3.4"
